[
  { "id": "voc:B2:auf dem neuesten Stand sein", "def": "To have the most recent information or knowledge." },
  { "id": "voc:B2:erneuerbare Energien", "def": "Energy from sources that do not run out, like sun and wind." },
  { "id": "voc:B2:die Emissionen", "def": "Gases or substances released into the air, especially pollution." },
  { "id": "voc:B2:der Kompromiss", "def": "An agreement reached when each side gives up something." },
  { "id": "voc:B2:ein Gesetz verabschieden", "def": "To formally approve a new law in parliament." },
  { "id": "voc:B2:der Vorgesetzte", "def": "A person who is in charge of others at work." },
  { "id": "voc:B2:die Abteilung", "def": "A separate section of a company or organisation." },
  { "id": "voc:B2:die Gehaltsverhandlung", "def": "A discussion about how much someone will be paid." },
  { "id": "voc:B2:die Forschung", "def": "Careful study done to discover new facts." },
  { "id": "voc:B2:das Experiment", "def": "A test done to discover or prove something." },
  { "id": "voc:B2:schädlich", "def": "Causing damage or harm." },
  { "id": "voc:B2:der Taifun", "def": "A violent tropical storm in the western Pacific." },
  { "id": "voc:B2:die Wolkendecke", "def": "The layer of clouds covering the sky." },
  { "id": "voc:B2:aufgewühlt", "def": "Emotionally stirred up and restless." },
  { "id": "voc:B2:der Hummer", "def": "A large sea animal with a hard shell and strong claws, eaten as food." },
  { "id": "voc:B2:die Vereinigten Arabischen Emirate", "def": "A country of seven states on the Arabian Peninsula." },
  { "id": "voc:B2:gerührt", "def": "Feeling gentle emotion, close to tears." },
  { "id": "voc:B2:misstrauisch", "def": "Not willing to trust; suspicious." },
  { "id": "voc:B2:sich sehnen", "def": "To feel a strong wish for something or someone." },
  { "id": "voc:B2:das Burnout", "def": "A state of deep exhaustion caused by long-term stress." },
  { "id": "voc:B2:überwältigt", "def": "Overcome by a strong feeling or by too much at once." },
  { "id": "voc:B2:das Gen", "def": "A unit in a cell that carries inherited traits from parents." },
  { "id": "voc:B2:der Einbauschrank", "def": "A cupboard built into the wall of a room." },
  { "id": "voc:B2:die Müllabfuhr", "def": "The service that takes away household rubbish." },
  { "id": "voc:B2:dicht besiedelt", "def": "Having many people living close together in an area." },
  { "id": "voc:B2:die Obdachlosigkeit", "def": "The state of having nowhere to live." },
  { "id": "voc:B2:die Stadtentwicklung", "def": "The planned growth and improvement of a city." },
  { "id": "voc:B2:das Engagement", "def": "Active involvement and effort in a cause or task." },
  { "id": "voc:B2:die Kaserne", "def": "A building where soldiers live." },
  { "id": "voc:B2:patrouillieren", "def": "To move around an area to guard or watch it." },
  { "id": "voc:B2:rekrutieren", "def": "To find and enlist new members or workers." },
  { "id": "voc:B2:strategisch", "def": "Planned carefully to achieve a long-term aim." },
  { "id": "voc:B2:das Hauptquartier", "def": "The main centre from which an organisation is run." },
  { "id": "voc:B2:das Schneebrett", "def": "A slab of snow that breaks loose and slides down a slope." },
  { "id": "voc:B2:die Tendenz", "def": "A general direction or inclination toward something." },
  { "id": "voc:B2:der Aspekt", "def": "One particular part or feature of something." },
  { "id": "voc:B2:die Voraussage", "def": "A statement about what will happen in the future." },
  { "id": "voc:B2:die Schlussfolgerung", "def": "A judgement reached by reasoning from facts." },
  { "id": "voc:B2:die Wahrnehmung", "def": "The way something is noticed or understood through the senses." },
  { "id": "voc:B2:die Erleichterung", "def": "The pleasant feeling when worry or pain goes away." },
  { "id": "voc:B2:die Zunahme", "def": "A rise in amount, size, or number." },
  { "id": "voc:B2:der Durchschnitt", "def": "The typical or middle value found by adding and dividing." },
  { "id": "voc:B2:beeinflussen", "def": "To have an effect on how something develops or behaves." },
  { "id": "voc:B2:zahlreich", "def": "Existing in large numbers; many." },
  { "id": "voc:B2:vorläufig", "def": "For the time being; not yet final." },
  { "id": "voc:B2:umstritten", "def": "Causing strong disagreement among people." },
  { "id": "voc:B2:hingegen", "def": "By contrast; however." },
  { "id": "voc:B2:vorausgesetzt", "def": "On the condition that." },
  { "id": "voc:B2:betont", "def": "Given special stress or importance." },
  { "id": "voc:B2:bislang", "def": "Up to the present time." },
  { "id": "voc:B2:erneut", "def": "Once more; another time." },
  { "id": "voc:B2:erstmals", "def": "On the first occasion." },
  { "id": "voc:B2:künftig", "def": "From now on; in the time to come." },
  { "id": "voc:B2:die Union", "def": "A group joined together for a common purpose." },
  { "id": "voc:B2:weiterhin", "def": "As before; also in addition." },
  { "id": "voc:B2:die Anfrage", "def": "A question or request for information." },
  { "id": "voc:B2:angeblich", "def": "Claimed to be true, but not proven." },
  { "id": "voc:B2:die Anklage", "def": "A formal statement that someone has committed a crime." },
  { "id": "voc:B2:beziehungsweise", "def": "A formal word meaning 'or rather' or 'respectively'." },
  { "id": "voc:B2:daraufhin", "def": "As a direct result; immediately after that." },
  { "id": "voc:B2:entgegen", "def": "In the opposite direction to; contrary to." },
  { "id": "voc:B2:entsprechend", "def": "Matching or suitable to something; accordingly." },
  { "id": "voc:B2:der Ermittler", "def": "A person who looks into a crime or matter to find facts." },
  { "id": "voc:B2:die Finanzierung", "def": "The provision of money for a project or purpose." },
  { "id": "voc:B2:die Gewerkschaft", "def": "An organisation that protects workers' rights." },
  { "id": "voc:B2:grundsätzlich", "def": "Concerning basic principles; as a general rule." },
  { "id": "voc:B2:die Initiative", "def": "A first step or plan to deal with a problem; also drive." },
  { "id": "voc:B2:kürzlich", "def": "Not long ago." },
  { "id": "voc:B2:maximal", "def": "As great as possible; at the upper limit." },
  { "id": "voc:B2:mehrfach", "def": "Happening or existing more than once." },
  { "id": "voc:B2:der Nachfolger", "def": "A person who takes over a role from another." },
  { "id": "voc:B2:das Personal", "def": "The people who work for an organisation." },
  { "id": "voc:B2:die Pressekonferenz", "def": "A meeting where news is given to journalists." },
  { "id": "voc:B2:die Redaktion", "def": "The people who prepare a publication; also the editing work." },
  { "id": "voc:B2:die Sitzung", "def": "A formal gathering to discuss or decide matters." },
  { "id": "voc:B2:die Stiftung", "def": "An organisation set up to support a cause with its funds." },
  { "id": "voc:B2:die Umsetzung", "def": "The act of putting a plan or idea into practice." },
  { "id": "voc:B2:das Verfahren", "def": "A set way of doing something; also a legal case." },
  { "id": "voc:B2:vollständig", "def": "Whole; with nothing missing." },
  { "id": "voc:B2:voran", "def": "Moving forward; in front." },
  { "id": "voc:B2:vorerst", "def": "For the present time; until further notice." },
  { "id": "voc:B2:weitgehend", "def": "To a great extent; for the most part." },
  { "id": "voc:B2:womöglich", "def": "Perhaps; it may be so." },
  { "id": "voc:B2:zugleich", "def": "Simultaneously; also." },
  { "id": "voc:B2:der Anbieter", "def": "A company or person that offers a product or service." },
  { "id": "voc:B2:ausgesprochen", "def": "To a marked degree; distinctly." },
  { "id": "voc:B2:die Berufung", "def": "An appointment to a post; also a legal appeal or a vocation." },
  { "id": "voc:B2:der Betreiber", "def": "A company or person that runs a facility or service." },
  { "id": "voc:B2:bundesweit", "def": "Across the whole country." },
  { "id": "voc:B2:derweil", "def": "During the same time; in the meantime." },
  { "id": "voc:B2:die Ebene", "def": "A flat area of land; also a level within a structure." },
  { "id": "voc:B2:die Einigung", "def": "The reaching of an agreement between sides." },
  { "id": "voc:B2:erforderlich", "def": "Needed or demanded for a purpose." },
  { "id": "voc:B2:die Erhöhung", "def": "A rise in amount or level." },
  { "id": "voc:B2:der Finanzminister", "def": "The government minister in charge of a country's money." },
  { "id": "voc:B2:hierzulande", "def": "In this country; here where we are." },
  { "id": "voc:B2:jüngst", "def": "Very recently; not long ago." },
  { "id": "voc:B2:die Klage", "def": "A statement of grievance; also a legal action in court." },
  { "id": "voc:B2:das Los", "def": "A ticket in a draw; also a person's fate or lot." },
  { "id": "voc:B2:mittels", "def": "Using a particular method or tool." },
  { "id": "voc:B2:namens", "def": "By the name of; also on behalf of." },
  { "id": "voc:B2:das Potenzial", "def": "The unused ability to develop or succeed in the future." },
  { "id": "voc:B2:die Sanierung", "def": "The repair and improvement of a building or area." },
  { "id": "voc:B2:die Stadtverwaltung", "def": "The body that runs the administration of a town or city." },
  { "id": "voc:B2:die Unfallstelle", "def": "The place where an accident happened." },
  { "id": "voc:B2:unmittelbar", "def": "Happening at once or with nothing in between." },
  { "id": "voc:B2:die Veröffentlichung", "def": "The act of making something available to the public." },
  { "id": "voc:B2:zeitweise", "def": "Now and then; for limited periods." },
  { "id": "voc:B2:äußerst", "def": "To the highest degree; very." },
  { "id": "voc:B2:die Übernahme", "def": "The act of taking control of something, such as a company." },
  { "id": "voc:B2:überwiegend", "def": "For the most part; mainly." },
  { "id": "voc:B2:die Abwehr", "def": "The act of protecting against attack; also the body's resistance." },
  { "id": "voc:B2:die Allianz", "def": "A union formed between groups or countries for a shared aim." },
  { "id": "voc:B2:die Angelegenheit", "def": "A subject or situation that must be dealt with." },
  { "id": "voc:B2:angesehen", "def": "Held in high regard by others." },
  { "id": "voc:B2:anlässlich", "def": "In connection with a particular event." },
  { "id": "voc:B2:das Anzeichen", "def": "Something that shows that a condition or event exists." },
  { "id": "voc:B2:ausdrücklich", "def": "Stated clearly and directly." },
  { "id": "voc:B2:die Ausstattung", "def": "The equipment and features that something is provided with." },
  { "id": "voc:B2:die Auszeichnung", "def": "An honour or prize given for achievement." },
  { "id": "voc:B2:die Begeisterung", "def": "Strong excitement and eager interest." },
  { "id": "voc:B2:die Bekämpfung", "def": "The effort to fight against or stop something harmful." },
  { "id": "voc:B2:belassen", "def": "To let something stay unchanged." },
  { "id": "voc:B2:die Bereitschaft", "def": "The state of being ready or willing to act." },
  { "id": "voc:B2:bestens", "def": "In the best possible way; excellently." },
  { "id": "voc:B2:binnen", "def": "Inside a stated period of time." },
  { "id": "voc:B2:die Darstellung", "def": "The way something is shown, described, or represented." },
  { "id": "voc:B2:die Ehre", "def": "Great respect, or a source of pride and good reputation." },
  { "id": "voc:B2:der Eigentümer", "def": "The person who legally owns something." },
  { "id": "voc:B2:eingeschränkt", "def": "Kept within limits; reduced." }
]
